ropwr/__init__.py
ropwr/_version.py
ropwr/base.py
ropwr/cvx.py
ropwr/cvx_qp.py
ropwr/cvx_socp.py
ropwr/direct.py
ropwr/matrices.py
ropwr-1.1.0.dist-info/LICENSE
ropwr-1.1.0.dist-info/METADATA
ropwr-1.1.0.dist-info/WHEEL
ropwr-1.1.0.dist-info/top_level.txt
ropwr-1.1.0.dist-info/RECORD
