Metadata-Version: 2.1
Name: ropwr
Version: 1.1.0
Summary: RoPWR: Robust Piecewise Regression
Home-page: https://github.com/guillermo-navas-palencia/ropwr
Author: Guillermo Navas-Palencia
Author-email: g.navas.palencia@gmail.com
License: Apache Licence 2.0
Platform: any
Classifier: Topic :: Scientific/Engineering :: Mathematics
Classifier: Topic :: Software Development :: Libraries
Classifier: Topic :: Software Development :: Libraries :: Python Modules
Classifier: Intended Audience :: Developers
Classifier: Intended Audience :: Education
Classifier: Intended Audience :: Science/Research
Classifier: License :: OSI Approved :: Apache Software License
Classifier: Programming Language :: Python :: 3
Requires-Python: >=3.7
Provides-Extra: test
Provides-Extra: ecos
License-File: LICENSE
